enigma/__init__.py
enigma/configurations.py
enigma/machine.py
enigma/object.py
enigmachine-1.0.dist-info/LICENSE
enigmachine-1.0.dist-info/METADATA
enigmachine-1.0.dist-info/WHEEL
enigmachine-1.0.dist-info/top_level.txt
enigmachine-1.0.dist-info/RECORD
