Metadata-Version: 2.1
Name: enigmachine
Version: 1.0
Summary: Engima chiper machine
Home-page: https://github.com/Fer14/enigmachine
Author: Fernando Cortés
Author-email: fcsancho14@gmail.com
License: MIT
Project-URL: Bug Tracker, https://github.com/Fer14/enigmachine/issues
Project-URL: Documentation, https://github.com/Fer14/enigmachine/
Project-URL: Source Code, https://github.com/Fer14/enigmachine/
Keywords: enigma machine cryptography cipher
Platform: UNKNOWN
Classifier: Programming Language :: Python :: 3
Classifier: License :: OSI Approved :: MIT License
License-File: LICENSE
Requires-Dist: tabulate
